bin2hpm/__init__.py
bin2hpm/__main__.py
bin2hpm/bitfile.py
bin2hpm/cli.py
bin2hpm/hpm.py
bin2hpm/hpm_conv.py
bin2hpm/rle.py
bin2hpm-0.2.1.dist-info/LICENSE.txt
bin2hpm-0.2.1.dist-info/METADATA
bin2hpm-0.2.1.dist-info/WHEEL
bin2hpm-0.2.1.dist-info/entry_points.txt
bin2hpm-0.2.1.dist-info/top_level.txt
bin2hpm-0.2.1.dist-info/RECORD
