Metadata-Version: 2.1
Name: bin2hpm
Version: 0.2.1
Summary: HPM.1 file conversion tool
Home-page: https://techlab.desy.de
Author: Patrick Huesmann
Author-email: patrick.huesmann@desy.de
License: BSD
Keywords: ipmi hpm microtca amc picmg update upgrade
Platform: UNKNOWN
Classifier: Programming Language :: Python :: 3.6
Classifier: Operating System :: OS Independent
Classifier: Environment :: Console
Classifier: License :: OSI Approved :: BSD License
Classifier: Intended Audience :: Developers
Classifier: Development Status :: 3 - Alpha
Requires-Python: >=3.6
License-File: LICENSE.txt
Requires-Dist: tqdm (>=4.61.0)
